aws_toolbox/__init__.py
aws_toolbox/cli.py
aws_toolbox/commands/__init__.py
aws_toolbox/commands/base_commands.py
aws_toolbox/commands/regions.py
aws_toolbox/commands/cloudformation/__init__.py
aws_toolbox/commands/cloudformation/cloudformation.py
aws_toolbox/commands/cloudformation/delete_stacks.py
aws_toolbox/commands/ec2/__init__.py
aws_toolbox/commands/ec2/delete_ami.py
aws_toolbox/commands/ec2/delete_snapshot.py
aws_toolbox/commands/ec2/describe_amis.py
aws_toolbox/commands/ec2/describe_key_pairs.py
aws_toolbox/commands/ec2/describe_snapshot.py
aws_toolbox/commands/ec2/ec2.py
aws_toolbox/commands/iam/__init__.py
aws_toolbox/commands/iam/delete_roles.py
aws_toolbox/commands/iam/iam.py
aws_toolbox/commands/s3/__init__.py
aws_toolbox/commands/s3/delete_bucket.py
aws_toolbox/commands/s3/s3.py
aws_toolbox/commands/secretsmanager/__init__.py
aws_toolbox/commands/secretsmanager/delete_secrets.py
aws_toolbox/commands/secretsmanager/list_secrets.py
aws_toolbox/commands/secretsmanager/secretsmanager.py
aws_toolbox/config/__init__.py
aws_toolbox/config/metadata.py
aws_toolbox/utils/__init__.py
aws_toolbox/utils/guiutils.py
aws_toolbox/utils/logutils.py
aws_toolbox/utils/time.py
aws_toolbox-0.0.6.dist-info/licenses/LICENSE
aws_toolbox-0.0.6.dist-info/METADATA
aws_toolbox-0.0.6.dist-info/WHEEL
aws_toolbox-0.0.6.dist-info/entry_points.txt
aws_toolbox-0.0.6.dist-info/top_level.txt
aws_toolbox-0.0.6.dist-info/RECORD
