Metadata-Version: 2.4
Name: aws-toolbox
Version: 0.0.6
Summary: AWS Toolbox
Home-page: https://github.com/gmarciani/aws-toolbox
Author: Giacomo Marciani
License: MIT License
Project-URL: Changelog, https://github.com/gmarciani/aws-toolbox/CHANGELOG.md
Project-URL: Issue Tracker, https://github.com/gmarciani/aws-toolbox/issues
Project-URL: Documentation, https://github.com/gmarciani/aws-toolbox
Classifier: Development Status :: 1 - Planning
Classifier: Environment :: Console
Classifier: Programming Language :: Python
Classifier: Programming Language :: Python :: 3
Classifier: Programming Language :: Python :: 3.7
Classifier: Programming Language :: Python :: 3.8
Classifier: Programming Language :: Python :: 3.9
Classifier: Programming Language :: Python :: 3.10
Classifier: Topic :: Scientific/Engineering
Classifier: License :: OSI Approved :: MIT License
Requires-Python: >=3.6
License-File: LICENSE
Requires-Dist: boto3~=1.40.8
Requires-Dist: click~=8.2.1
Requires-Dist: colored~=2.3.1
Requires-Dist: pyfiglet~=1.0.3
Requires-Dist: setuptools~=80.9.0
Dynamic: author
Dynamic: classifier
Dynamic: description
Dynamic: description-content-type
Dynamic: home-page
Dynamic: license
Dynamic: license-file
Dynamic: project-url
Dynamic: requires-dist
Dynamic: requires-python
Dynamic: summary
